<?xml version="1.0"?>
<!DOCTYPE hibernate-mapping PUBLIC "-//Hibernate/Hibernate Mapping DTD 3.0//EN"
"http://hibernate.sourceforge.net/hibernate-mapping-3.0.dtd">
<!-- 
    Mapping file autogenerated by MyEclipse - Hibernate Tools
-->
<hibernate-mapping>
	<class name="com.acs.ts.vector.ws.tollrate.persistence.TVehicleClass" table="T_VEHICLE_CLASS" lazy="false">
        <id name="agencyClass" column="AGENCY_CLASS" type="java.lang.Long">
            <generator class="assigned"/>
        </id>
        <property name="classDescription" column="CLASS_DESCRIPTION" type="java.lang.String" />
        <property name="agencyId" column="AGENCY_ID" type="java.lang.String" />
    </class>
    
	<sql-query name = "GET_VEHICLECLASS">
		SELECT agencyClass, classDescription FROM TVehicleClass where agencyId=8
	</sql-query>
</hibernate-mapping>